<?xml version="1.0"?>
<APList><version>1.010000</version><dict><key>bgColor</key><str>255255255255</str><key>childIndexes</key><str>2,4,8,12</str><key>className</key><str>APSSymbol</str><key>index</key><int>1</int><key>nResources</key><int>24</int><key>parentIndex</key><int>0</int><key>position</key><str>0,0</str><key>prologues</key><str>16,24</str><key>resources</key><array><str>APSSymbol</str><dict><key>childIndexes</key><str>3</str><key>className</key><str>APSGraphicGroup</str><key>index</key><int>2</int><key>parentIndex</key><int>1</int><key>position</key><str>236.027,181.197</str><key>size</key><str>80,96</str></dict><dict><key>className</key><str>APSSprite</str><key>imageHolderCode</key><str>13</str><key>index</key><int>3</int><key>parentIndex</key><int>2</int><key>position</key><str>40,48</str><key>size</key><str>80,96</str></dict><dict><key>TBeginLinkers</key><str>5</str><key>childIndexes</key><str>7</str><key>className</key><str>APSGraphicGroup</str><key>index</key><int>4</int><key>parentIndex</key><int>1</int><key>position</key><str>59.2291,37.4379</str><key>size</key><str>63.2969,38</str></dict><dict><key>actionGroupIndex</key><int>0</int><key>className</key><str>APSLinkerAction</str><key>duration</key><real>0.05</real><key>index</key><int>5</int><key>noTrigRT</key><bool>true</bool><key>startTime</key><real>0</real><key>tActionIdx</key><int>6</int><key>targetGraphicIndex</key><int>4</int></dict><dict><key>actionGroupIndex</key><int>0</int><key>actionIndexes</key><str>21</str><key>className</key><str>APSActionGroup</str><key>duration</key><real>1</real><key>index</key><int>6</int><key>startTime</key><real>0</real><key>tag</key><str>ActionGroup2</str><key>targetGraphicIndex</key><int>1</int></dict><dict><key>className</key><str>APSSprite</str><key>imageHolderCode</key><str>205</str><key>index</key><int>7</int><key>parentIndex</key><int>4</int><key>position</key><str>31.6484,19</str><key>size</key><str>63.2969,38</str></dict><dict><key>TMovedLinkers</key><str>9</str><key>childIndexes</key><str>11</str><key>className</key><str>APSGraphicGroup</str><key>index</key><int>8</int><key>parentIndex</key><int>1</int><key>position</key><str>240,37.4379</str><key>size</key><str>93.5312,38</str></dict><dict><key>actionGroupIndex</key><int>0</int><key>className</key><str>APSLinkerAction</str><key>duration</key><real>0.05</real><key>index</key><int>9</int><key>noTrigRT</key><bool>true</bool><key>startTime</key><real>0</real><key>tActionIdx</key><int>10</int><key>targetGraphicIndex</key><int>8</int></dict><dict><key>actionGroupIndex</key><int>0</int><key>actionIndexes</key><str>22</str><key>className</key><str>APSActionGroup</str><key>duration</key><real>0.5</real><key>index</key><int>10</int><key>startTime</key><real>0</real><key>tag</key><str>ActionGroup3</str><key>targetGraphicIndex</key><int>1</int></dict><dict><key>className</key><str>APSSprite</str><key>imageHolderCode</key><str>206</str><key>index</key><int>11</int><key>parentIndex</key><int>8</int><key>position</key><str>46.7656,19</str><key>size</key><str>93.5312,38</str></dict><dict><key>TEndLinkers</key><str>13</str><key>childIndexes</key><str>15</str><key>className</key><str>APSGraphicGroup</str><key>index</key><int>12</int><key>parentIndex</key><int>1</int><key>position</key><str>419.824,37.4379</str><key>size</key><str>81.125,38</str></dict><dict><key>actionGroupIndex</key><int>0</int><key>className</key><str>APSLinkerAction</str><key>duration</key><real>0.05</real><key>index</key><int>13</int><key>noTrigRT</key><bool>true</bool><key>startTime</key><real>0</real><key>tActionIdx</key><int>14</int><key>targetGraphicIndex</key><int>12</int></dict><dict><key>actionGroupIndex</key><int>0</int><key>actionIndexes</key><str>23</str><key>className</key><str>APSActionGroup</str><key>duration</key><real>1</real><key>index</key><int>14</int><key>startTime</key><real>0</real><key>tag</key><str>ActionGroup4</str><key>targetGraphicIndex</key><int>1</int></dict><dict><key>className</key><str>APSSprite</str><key>imageHolderCode</key><str>207</str><key>index</key><int>15</int><key>parentIndex</key><int>12</int><key>position</key><str>40.5625,19</str><key>size</key><str>81.125,38</str></dict><dict><key>actionGroupIndex</key><int>0</int><key>actionIndexes</key><str>17,18,19,20</str><key>className</key><str>APSActionGroup</str><key>duration</key><real>1</real><key>index</key><int>16</int><key>prologue</key><bool>true</bool><key>startTime</key><real>0</real><key>tag</key><str>ActionGroup1</str><key>targetGraphicIndex</key><int>1</int></dict><dict><key>actionGroupIndex</key><int>16</int><key>className</key><str>APSVisibilityAction</str><key>duration</key><real>0.05</real><key>index</key><int>17</int><key>startTime</key><real>0</real><key>targetGraphicIndex</key><int>2</int></dict><dict><key>actionGroupIndex</key><int>16</int><key>className</key><str>APSVisibilityAction</str><key>duration</key><real>0.05</real><key>index</key><int>18</int><key>startTime</key><real>0</real><key>targetGraphicIndex</key><int>4</int></dict><dict><key>actionGroupIndex</key><int>16</int><key>className</key><str>APSVisibilityAction</str><key>duration</key><real>0.05</real><key>index</key><int>19</int><key>startTime</key><real>0</real><key>targetGraphicIndex</key><int>8</int></dict><dict><key>actionGroupIndex</key><int>16</int><key>className</key><str>APSVisibilityAction</str><key>duration</key><real>0.05</real><key>index</key><int>20</int><key>startTime</key><real>0</real><key>targetGraphicIndex</key><int>12</int></dict><dict><key>actionGroupIndex</key><int>6</int><key>className</key><str>APSMoveAction</str><key>duration</key><real>1</real><key>endPosition</key><str>-112.819,0</str><key>index</key><int>21</int><key>startTime</key><real>0</real><key>targetGraphicIndex</key><int>2</int><key>timingFactor</key><real>2</real></dict><dict><key>actionGroupIndex</key><int>10</int><key>className</key><str>APSRotationAction</str><key>duration</key><real>0.5</real><key>endRotation</key><real>90.4736</real><key>index</key><int>22</int><key>startTime</key><real>0</real><key>targetGraphicIndex</key><int>2</int><key>timingFactor</key><real>2</real></dict><dict><key>actionGroupIndex</key><int>14</int><key>className</key><str>APSMoveAction</str><key>duration</key><real>1</real><key>endPosition</key><str>82.5178,-7.27297e-06</str><key>index</key><int>23</int><key>startTime</key><real>0</real><key>targetGraphicIndex</key><int>2</int><key>timingFactor</key><real>2</real></dict><dict><key>actionGroupIndex</key><int>0</int><key>actionIndexes</key><str></str><key>className</key><str>APSActionGroup</str><key>duration</key><real>0</real><key>index</key><int>24</int><key>prologue</key><bool>true</bool><key>startTime</key><real>0</real><key>tag</key><str>AutoTriggerActionGroup</str><key>targetGraphicIndex</key><int>1</int></dict></array><key>size</key><str>480,320</str><key>tBeginLns</key><str>4</str><key>tEndLns</key><str>12</str><key>tMovedLns</key><str>8</str><key>tag</key><str>Symbol1</str></dict></APList>
